rs3_api/__init__.py
rs3_api/hiscores/__init__.py
rs3_api/hiscores/exceptions.py
rs3_api/hiscores/hiscore.py
rs3_api/hiscores/types.py
rs3_api/hiscores/clan_hiscore/__init__.py
rs3_api/hiscores/clan_hiscore/clan_members_hiscore.py
rs3_api/hiscores/seasonal_hiscore/__init__.py
rs3_api/hiscores/seasonal_hiscore/seasonal_details_hiscore.py
rs3_api/hiscores/seasonal_hiscore/user_seasonal_hiscore.py
rs3_api/hiscores/user_hiscore/__init__.py
rs3_api/hiscores/user_hiscore/user_hiscore.py
rs3_api/utils/__init__.py
rs3_api/utils/const.py
rs3_api/utils/xp_table.py
rs3_api-0.1.0.dist-info/LICENSE
rs3_api-0.1.0.dist-info/METADATA
rs3_api-0.1.0.dist-info/WHEEL
rs3_api-0.1.0.dist-info/top_level.txt
rs3_api-0.1.0.dist-info/RECORD
