Metadata-Version: 2.1
Name: rs3-api
Version: 0.1.0
Summary: A wrapper for Runescape 3 API to make it easier to work.
Author-email: Luciano Feder <lucianoo.feder@gmail.com>
Project-URL: homepage, https://github.com/lucianofeder/runescape3-api-wrapper
Project-URL: documentation, https://github.com/lucianofeder/runescape3-api-wrapper
Project-URL: repository, https://github.com/lucianofeder/runescape3-api-wrapper
Keywords: runescape3,rs3,runescape,api
Classifier: Topic :: Software Development
Classifier: License :: OSI Approved :: MIT License
Classifier: Operating System :: OS Independent
Requires-Python: >=3.7
License-File: LICENSE
Requires-Dist: requests
